{
  "english": "undercarriage",
  "phat_am": "ˈandəkӕridʒ",
  "list_english": [
    {
      "type_word": "noun",
      "list_definition": [
        {
          "mean_english": "bộ phận hạ cánh máy bay",
          "definition": "the landing-gear of an aircraft",
          "world_new": [
            "aircraft"
          ],
          "list_ex_of_definition": [
            {
              "ex_of_definition": "The pilot had some difficulty in lowering the undercarriage.",
              "world_new": [
                "pilot",
                "difficulty",
                "lowering"
              ]
            }
          ]
        }
      ]
    }
  ],
  "list_ex_of_english": [
    "This is where they had the heavier undercarriage, and this is something which we on our professional side were advised to fit to our aircraft.",
    "That is a very uneconomical proposition, and as aircraft get bigger so the undercarriage elements will also continue to grow.",
    "It is slow, and has a fixed undercarriage.",
    "The robot is 5 metres long, 4 metres wide and 1.5 metres high, with the rotor 2.5 metres in diameter and the undercarriage retractable.",
    "For me, the greatest joy of flying is the reassuring moment when the undercarriage makes firm and continued re-contact with terra firma.",
    "How is it that we do not find incorporated in such machines devices like retractable undercarriages, slots and variable pitched propellers?",
    "One firm which makes undercarriages for aeroplanes has now developed a hydraulic pit prop.",
    "There has been a suggestion that there have been problems in developing the undercarriage."
  ],
  "list_see_also": [],
  "list_browse": [
    "under someone’s thumb",
    "under the sun",
    "under the weather",
    "under way",
    "undercarriage",
    "underclothes",
    "underclothing",
    "undercover",
    "undercut"
  ],
  "list_img": [
    {
      "link_thumb": "https://live.staticflickr.com/65535/51808398887_acde0ecf67_n.jpg",
      "link_img": "https://live.staticflickr.com/65535/51808398887_2107316bb9_o.png",
      "id_image": "undercarriage_1619274"
    }
  ]
}